[
    {
        "title": "test",
        "text": "test",
        "id": "835c"
    },
    {
        "title": "test 2",
        "text": "test 2",
        "id": "bc8c"
    },
    {
        "title": "test 3",
        "text": "test 3",
        "id": "4884"
    },
    {
        "title": "test 3",
        "text": "test 3",
        "id": "2f82"
    },
    {
        "title": "test 4",
        "text": "test 4",
        "id": "7f81"
    },
    {
        "title": "test 5",
        "text": "test 65",
        "id": "a623"
    },
    {
        "title": "test 6",
        "text": "test 6",
        "id": "ba5b"
    },
    {
        "title": "test 9",
        "text": "test 9",
        "id": "7446"
    }
]